main.py
yangke/__init__.py
yangke/base.py
yangke/core.py
yangke/test1.py
yangke/common/Interact.py
yangke/common/KeysTransfer.py
yangke/common/QtImporter.py
yangke/common/__init__.py
yangke/common/config.py
yangke/common/crawler.py
yangke/common/dijstra.py
yangke/common/dll_operate.py
yangke/common/fileOperate.py
yangke/common/http_client.py
yangke/common/lunar.py
yangke/common/ml.py
yangke/common/office.py
yangke/common/qt.py
yangke/common/resnet_torch.py
yangke/common/serial_port.py
yangke/common/yk.png
yangke/common/win/__init__.py
yangke/common/win/dxinput.py
yangke/common/win/keyboard.py
yangke/common/win/mouse_key_hook.py
yangke/common/win/send_input.py
yangke/common/win/win_x64.py
yangke/dataset/PIDB.py
yangke/dataset/YKSqlalchemy.py
yangke/dataset/__init__.py
yangke/dataset/loadStandardDataset.py
yangke/dataset/mysql.py
yangke/dataset/neo4j.py
yangke/dataset/sqlite.py
yangke/dataset/utils.py
yangke/ebsilon/ALPHA.py
yangke/ebsilon/__init__.py
yangke/ebsilon/ebsilon.py
yangke/ebsilon/ebsilon4js.py
yangke/ebsilon/ebsilon_client.py
yangke/ebsilon/ebsilon_server.py
yangke/ebsilon/graphicsview.py
yangke/ebsilon/values.py
yangke/ebsilon/重庆两江.py
yangke/ebsilon/Plugins/__init__.py
yangke/ebsilon/UI/MainWindow_PyQt5.py
yangke/ebsilon/UI/__init__.py
yangke/ebsilon/UI/content.py
yangke/ebsilon/constant/__init__.py
yangke/ebsilon/constant/constant.py
yangke/face/__init__.py
yangke/face/face.py
yangke/face/helmet.py
yangke/face/tencent.py
yangke/face/tencent_data_struct.py
yangke/game/__init__.py
yangke/game/auto.py
yangke/game/auto测试.py
yangke/game/gf.py
yangke/game/gf_ui.py
yangke/nlp/HuggingFace.py
yangke/nlp/__init__.py
yangke/nlp/chatgpt.py
yangke/nlp/ltp.py
yangke/nlp/wechat.py
yangke/office/__init__.py
yangke/office/refprop.js
yangke/office/wps宏.js
yangke/office/xlwings安装.py
yangke/office/冷端优化.js
yangke/office/直接空冷系统.js
yangke/panda/__init__.py
yangke/panda/flow.py
yangke/panda/main.py
yangke/panda/definition/__init__.py
yangke/panda/nsh/__init__.py
yangke-2.0.24.dist-info/METADATA
yangke-2.0.24.dist-info/WHEEL
yangke-2.0.24.dist-info/top_level.txt
yangke-2.0.24.dist-info/RECORD
