Metadata-Version: 2.1
Name: yangke
Version: 2.0.24
Summary: 个人工具综合平台，包含常用工具，网络爬虫，知识图谱，神经网络预测等工具
Home-page: https://gitee.com/yangke02/lib4python
Author: 杨可
Author-email: yangyangyangkekeke@qq.com
License: MIT
Project-URL: Bug Tracter, https://gitee.com/yangke02/lib4python
Project-URL: Documentation, https://gitee.com/yangke02/lib4python
Project-URL: Source Code, https://gitee.com/yangke02/lib4python
Project-URL: Funding, https://gitee.com/yangke02/lib4python
Keywords: yangke
Classifier: Development Status :: 4 - Beta
Classifier: Intended Audience :: Developers
Classifier: Topic :: Software Development :: Build Tools
Classifier: License :: OSI Approved :: MIT License
Classifier: Natural Language :: Chinese (Simplified)
Classifier: Programming Language :: Python :: 3
Classifier: Operating System :: Microsoft :: Windows
Requires-Python: >=3.6
Requires-Dist: pandas>=1.3.0
Requires-Dist: pyyaml>=5.2
Requires-Dist: json5>=0.8.5
Requires-Dist: dill>=0.3.3
Requires-Dist: babel>=2.9
Requires-Dist: pathlib2
Requires-Dist: pillow>=7.0.0
Requires-Dist: cmake
Requires-Dist: loguru
Requires-Dist: apscheduler
Requires-Dist: matplotlib>=3.5.0
Requires-Dist: openpyxl>3
Requires-Dist: pyKriging
Requires-Dist: opencv-python
Requires-Dist: psutil
Requires-Dist: markupsafe>=2.1.1
Requires-Dist: pyecharts
Requires-Dist: iapws>=1.5
Requires-Dist: qt-material
Provides-Extra: all
Requires-Dist: requests>=2.22.0; extra == "all"
Requires-Dist: cryptography>=3.1.1; extra == "all"
Requires-Dist: sqlalchemy<=1.4.39; extra == "all"
Requires-Dist: waitress>=1.4.4; extra == "all"
Requires-Dist: openpyxl>=3.0.7; extra == "all"
Requires-Dist: pymysql>=0.9.3; extra == "all"
Requires-Dist: lxml; extra == "all"
Requires-Dist: python-docx>1.1.0; extra == "all"
Requires-Dist: selenium>=3.141.0; extra == "all"
Requires-Dist: scrapy>=2.0.0; extra == "all"
Requires-Dist: waitress; extra == "all"
Requires-Dist: cmake>=3.18.2; extra == "all"
Requires-Dist: pywin32; extra == "all"
Requires-Dist: gevent-websocket; extra == "all"
Requires-Dist: opencv-python>=4.2.0; extra == "all"
Requires-Dist: pypiwin32; extra == "all"
Requires-Dist: PyQt6-QScintillaxlrd>2.0; extra == "all"
Requires-Dist: sqlalchemy>=1.3.23; extra == "all"
Requires-Dist: plotly; extra == "all"
Requires-Dist: python-docx; extra == "all"
Requires-Dist: pillow>=7.0.0; extra == "all"
Requires-Dist: PyQt6-WebEngine; extra == "all"
Requires-Dist: flask-cors>=3.0.8; extra == "all"
Requires-Dist: flask>=1.1.2; extra == "all"
Requires-Dist: paddlepaddle; extra == "all"
Requires-Dist: mysql-connector-python>=8.0.24; extra == "all"
Requires-Dist: twisted>=20.3.0; extra == "all"
Requires-Dist: DBUtils>=1.3; extra == "all"
Requires-Dist: tushare>=1.2.48; extra == "all"
Requires-Dist: boost; extra == "all"
Requires-Dist: iapws>=1.5.2; extra == "all"
Requires-Dist: PyQt6; extra == "all"
Requires-Dist: gevent>=20.5.0; extra == "all"
Requires-Dist: pygame; extra == "all"
Requires-Dist: optuna; extra == "all"
Provides-Extra: database
Requires-Dist: pymysql>=0.9.3; extra == "database"
Requires-Dist: DBUtils>=1.3; extra == "database"
Requires-Dist: cryptography>=3.1.1; extra == "database"
Requires-Dist: python-docx; extra == "database"
Requires-Dist: mysql-connector-python>=8.0.24; extra == "database"
Requires-Dist: sqlalchemy<=1.4.39; extra == "database"
Provides-Extra: gameserver
Requires-Dist: twisted>=20.3.0; extra == "gameserver"
Requires-Dist: flask>=1.1.2; extra == "gameserver"
Requires-Dist: flask-cors>=3.0.8; extra == "gameserver"
Requires-Dist: requests>=2.22.0; extra == "gameserver"
Requires-Dist: gevent>=20.5.0; extra == "gameserver"
Requires-Dist: gevent-websocket; extra == "gameserver"
Requires-Dist: waitress>=1.4.4; extra == "gameserver"
Requires-Dist: lxml; extra == "gameserver"
Provides-Extra: imagerecognition
Requires-Dist: opencv-python>=4.2.0; extra == "imagerecognition"
Requires-Dist: cmake>=3.18.2; extra == "imagerecognition"
Requires-Dist: boost; extra == "imagerecognition"
Requires-Dist: pillow>=7.0.0; extra == "imagerecognition"
Requires-Dist: requests>=2.22.0; extra == "imagerecognition"
Requires-Dist: optuna; extra == "imagerecognition"
Requires-Dist: plotly; extra == "imagerecognition"
Requires-Dist: paddlepaddle; extra == "imagerecognition"
Provides-Extra: performance
Requires-Dist: iapws>=1.5.2; extra == "performance"
Requires-Dist: pygame; extra == "performance"
Requires-Dist: PyQt6; extra == "performance"
Requires-Dist: PyQt6-WebEngine; extra == "performance"
Requires-Dist: PyQt6-QScintillaxlrd>2.0; extra == "performance"
Requires-Dist: openpyxl>=3.0.7; extra == "performance"
Requires-Dist: python-docx>1.1.0; extra == "performance"
Requires-Dist: pywin32; extra == "performance"
Provides-Extra: stock
Requires-Dist: tushare>=1.2.48; extra == "stock"
Requires-Dist: scrapy>=2.0.0; extra == "stock"
Requires-Dist: pymysql>=0.9.3; extra == "stock"
Requires-Dist: DBUtils>=1.3; extra == "stock"
Requires-Dist: selenium>=3.141.0; extra == "stock"
Requires-Dist: mysql-connector-python>=8.0.24; extra == "stock"
Requires-Dist: sqlalchemy>=1.3.23; extra == "stock"
Provides-Extra: ugly
Requires-Dist: dlib>=19.17.0; extra == "ugly"
Requires-Dist: torch>=1.4.0; extra == "ugly"
Requires-Dist: scikit-learn; extra == "ugly"
Requires-Dist: scipy; extra == "ugly"
Requires-Dist: PyQt6-WebEngine; extra == "ugly"
Requires-Dist: pyWinhook>=1.6.2; extra == "ugly"
Requires-Dist: scikit-image>=0.19.3; extra == "ugly"
Requires-Dist: lmdb>=1.3.0; extra == "ugly"
Requires-Dist: orjson>3.7.3; extra == "ugly"
Requires-Dist: tensorflow>=2.8.0; extra == "ugly"
Requires-Dist: torch>=1.11.0; extra == "ugly"
Requires-Dist: paddleocr>=2.0.1; extra == "ugly"
Provides-Extra: web
Requires-Dist: flask>=1.1.2; extra == "web"
Requires-Dist: Flask-Cors>=3.0.8; extra == "web"
Requires-Dist: waitress; extra == "web"
Provides-Extra: windows
Requires-Dist: pypiwin32; extra == "windows"
